MANIFEST.in
README.md
requirements.txt
setup.py
hee/__init__.py
hee/app_template.conf
hee/heeconfig.py
hee/heeframework.py
hee/log4p_template.json
hee/rdb.py
hee/rdb_mysql.py
heeframework.egg-info/PKG-INFO
heeframework.egg-info/SOURCES.txt
heeframework.egg-info/dependency_links.txt
heeframework.egg-info/requires.txt
heeframework.egg-info/top_level.txt