Metadata-Version: 2.1
Name: heeframework
Version: 1.0.35
Summary: A lightweight IOC container framework
Home-page: https://github.com/marchsun/heeframework
Author: Yanhu Zou
Author-email: zyh5160@qq.com
License: MIT
Keywords: ioc,web,dependency,dependencies
Platform: UNKNOWN
Classifier: Intended Audience :: Developers
Classifier: License :: OSI Approved :: MIT License
Classifier: Natural Language :: English
Classifier: Programming Language :: Python :: 3.6
Requires-Python: >=3.4.0
